norse_op.pyd
norse/__init__.py
norse/__main__.py
norse/benchmark/__init__.py
norse/benchmark/benchmark.py
norse/benchmark/bindsnet_lif.py
norse/benchmark/genn_lif.py
norse/benchmark/main.py
norse/benchmark/norse_lif.py
norse/benchmark/plot.py
norse/dataset/__init__.py
norse/dataset/memory.py
norse/dataset/speech_commands.py
norse/dataset/spiking_heidelberg.py
norse/task/__init__.py
norse/task/__main__.py
norse/task/cartpole.py
norse/task/cifar10.py
norse/task/correlation_experiment.py
norse/task/memory.py
norse/task/mnist.py
norse/task/mnist_pl.py
norse/torch/__init__.py
norse/torch/functional/__init__.py
norse/torch/functional/coba_lif.py
norse/torch/functional/correlation_sensor.py
norse/torch/functional/decode.py
norse/torch/functional/encode.py
norse/torch/functional/filter.py
norse/torch/functional/heaviside.py
norse/torch/functional/iaf.py
norse/torch/functional/izhikevich.py
norse/torch/functional/leaky_integrator.py
norse/torch/functional/lif.py
norse/torch/functional/lif_adex.py
norse/torch/functional/lif_adex_refrac.py
norse/torch/functional/lif_box.py
norse/torch/functional/lif_correlation.py
norse/torch/functional/lif_ex.py
norse/torch/functional/lif_mc.py
norse/torch/functional/lif_mc_refrac.py
norse/torch/functional/lif_refrac.py
norse/torch/functional/lift.py
norse/torch/functional/logical.py
norse/torch/functional/lsnn.py
norse/torch/functional/regularization.py
norse/torch/functional/spikes_to_times_decoder.py
norse/torch/functional/stdp.py
norse/torch/functional/stdp_sensor.py
norse/torch/functional/superspike.py
norse/torch/functional/threshold.py
norse/torch/functional/tsodyks_makram.py
norse/torch/functional/adjoint/__init__.py
norse/torch/functional/adjoint/coba_lif_adjoint.py
norse/torch/functional/adjoint/lif_adjoint.py
norse/torch/functional/adjoint/lif_mc_adjoint.py
norse/torch/functional/adjoint/lif_mc_refrac_adjoint.py
norse/torch/functional/adjoint/lif_refrac_adjoint.py
norse/torch/functional/adjoint/lsnn_adjoint.py
norse-1.0.0.dist-info/LICENSE
norse-1.0.0.dist-info/METADATA
norse-1.0.0.dist-info/WHEEL
norse-1.0.0.dist-info/top_level.txt
norse-1.0.0.dist-info/RECORD
