Metadata-Version: 2.1
Name: norse
Version: 1.0.0
Summary: A library for deep learning with spiking neural networks
Home-page: http://github.com/norse/norse
Author: Christian Pehle, Jens E. Pedersen
Author-email: christian.pehle@gmail.com, jens@jepedersen.dk
License: UNKNOWN
Keywords: machine learning spiking neural networks
Platform: UNKNOWN
Classifier: Development Status :: 5 - Production/Stable
Classifier: Intended Audience :: Developers
Classifier: Intended Audience :: Education
Classifier: Intended Audience :: Science/Research
Classifier: Programming Language :: Python :: 3.7
Classifier: Programming Language :: Python :: 3.8
Classifier: Programming Language :: Python :: 3.9
Classifier: Topic :: Scientific/Engineering
Classifier: Topic :: Scientific/Engineering :: Mathematics
Classifier: Topic :: Scientific/Engineering :: Artificial Intelligence
Classifier: Topic :: Software Development
Classifier: Topic :: Software Development :: Libraries
Classifier: Topic :: Software Development :: Libraries :: Python Modules
Requires-Dist: numpy
Requires-Dist: torch (>=1.9.0)
Requires-Dist: torchvision (>=0.10.0)
